feudalAdapter-0.7.3.data/data/etc/feudal/feudal_adapter_template.conf
feudalAdapter-0.7.3.data/data/etc/feudal/templates/admin.deploy.template
feudalAdapter-0.7.3.data/data/etc/feudal/templates/admin.deploy.update.template
feudalAdapter-0.7.3.data/data/etc/feudal/templates/admin.test.template
feudalAdapter-0.7.3.data/data/etc/feudal/templates/admin.update.template
feudalAdapter-0.7.3.data/data/etc/feudal/templates/unknown.template
feudalAdapter-0.7.3.data/data/etc/feudal/templates/user.deploy.template
feudalAdapter-0.7.3.data/data/etc/feudal/templates/user.deploy.update.template
feudalAdapter-0.7.3.data/data/etc/feudal/templates/user.update.template
feudal_globalconfig/__init__.py
feudal_globalconfig/globalconfig.py
ldf_adapter/__init__.py
ldf_adapter/cmdline_params.py
ldf_adapter/config.py
ldf_adapter/eduperson.py
ldf_adapter/feudal_simulator.py
ldf_adapter/interface.py
ldf_adapter/logsetup.py
ldf_adapter/name_generators.py
ldf_adapter/results.py
ldf_adapter/userinfo.py
ldf_adapter/utils.py
ldf_adapter/approval/__init__.py
ldf_adapter/approval/models.py
ldf_adapter/approval/db/__init__.py
ldf_adapter/approval/db/generic.py
ldf_adapter/approval/db/sqlite.py
ldf_adapter/backend/__init__.py
ldf_adapter/backend/bwidm.py
ldf_adapter/backend/generic.py
ldf_adapter/backend/hooks.py
ldf_adapter/backend/ldap.py
ldf_adapter/backend/local_unix.py
ldf_adapter/notifier/__init__.py
ldf_adapter/notifier/courier.py
ldf_adapter/notifier/email.py
ldf_adapter/notifier/generic.py
feudalAdapter-0.7.3.dist-info/LICENSE
feudalAdapter-0.7.3.dist-info/METADATA
feudalAdapter-0.7.3.dist-info/WHEEL
feudalAdapter-0.7.3.dist-info/entry_points.txt
feudalAdapter-0.7.3.dist-info/pbr.json
feudalAdapter-0.7.3.dist-info/top_level.txt
feudalAdapter-0.7.3.dist-info/RECORD
