Metadata-Version: 2.1
Name: feudalAdapter
Version: 0.7.3
Summary: Adapter to connect provisioning events with a backend
Home-page: https://codebase.helmholtz.cloud/m-team/feudal/feudal_adapter_ldf
Author: Joshua Bachmeier
Author-email: joshua.bachmeier@student.kit.edu
License: MIT
Project-URL: Bug Tracker, https://codebase.helmholtz.cloud/m-team/feudal/feudal_adapter_ldf/issues
Project-URL: Documentation, https://codebase.helmholtz.cloud/m-team/feudal/feudal_adapter_ldf
Classifier: Programming Language :: Python :: 3
Classifier: License :: OSI Approved :: MIT License
Classifier: Operating System :: POSIX
Classifier: Operating System :: POSIX :: Linux
Classifier: Environment :: Console
Classifier: Intended Audience :: System Administrators
Classifier: Natural Language :: English
Classifier: Topic :: System :: Systems Administration
Classifier: Topic :: System :: Systems Administration :: Authentication/Directory
License-File: LICENSE
Requires-Dist: argparse >=1.4.0
Requires-Dist: backcall >=0.1.0
Requires-Dist: certifi >=2019.6.16
Requires-Dist: chardet >=3.0.4
Requires-Dist: decorator >=4.4.0
Requires-Dist: idna >=2.8
Requires-Dist: ipython >=7.7.0
Requires-Dist: ipython-genutils >=0.2.0
Requires-Dist: jedi >=0.14.1
Requires-Dist: parso >=0.5.1
Requires-Dist: pexpect >=4.7.0
Requires-Dist: pickleshare >=0.7.5
Requires-Dist: prompt-toolkit >=2.0.9
Requires-Dist: ptyprocess >=0.6.0
Requires-Dist: Pygments >=2.4.2
Requires-Dist: regex >=2019.6.8
Requires-Dist: requests >=2.22.0
Requires-Dist: requests-cache >=0.4.13
Requires-Dist: six >=1.12.0
Requires-Dist: traitlets >=4.3.2
Requires-Dist: Unidecode >=1.1.1
Requires-Dist: urllib3 >=1.25.3
Requires-Dist: wcwidth >=0.1.7
Requires-Dist: ldap3 >=2.9.1
Requires-Dist: trycourier >=0.1.0
